exguard.py
exguard-0.2.1.dist-info/DESCRIPTION.rst
exguard-0.2.1.dist-info/METADATA
exguard-0.2.1.dist-info/RECORD
exguard-0.2.1.dist-info/WHEEL
exguard-0.2.1.dist-info/metadata.json
exguard-0.2.1.dist-info/top_level.txt
