Metadata-Version: 2.0
Name: exguard
Version: 0.2.1
Summary: UNKNOWN
Home-page: https://edugit.org/Veripeditus/exguard
Author: Eike Tim Jesinghaus
Author-email: eike@naturalnet.de
License: UNKNOWN
Platform: UNKNOWN
Classifier: Development Status :: 4 - Beta
Classifier: Intended Audience :: Developers
Classifier: License :: OSI Approved :: MIT License
Classifier: Programming Language :: Python :: 3
Classifier: Topic :: Software Development :: Libraries :: Python Modules
Requires-Python: >=3.5
